.gitignore
AUTHORS
COPYING
ChangeLog
LICENSE
NEWS
README.md
TODO
bootstrap.sh
plist.py
setup.py
Docs/Events
genpp/__init__.py
genpp/align.py
genpp/apache-plugin.py
genpp/arp-plugin.py
genpp/asm-plugin.py
genpp/bind-plugin.py
genpp/blkdev-plugin.py
genpp/blkid-plugin.py
genpp/chrony-plugin.py
genpp/codegen.py
genpp/crontab-plugin.py
genpp/csv-plugin.py
genpp/cups-plugin.py
genpp/df-plugin.py
genpp/exports-plugin.py
genpp/free-plugin.py
genpp/fstab-plugin.py
genpp/grub-plugin.py
genpp/help-plugin.py
genpp/hosts-plugin.py
genpp/ifcfg-plugin.py
genpp/ini-plugin.py
genpp/ins-plugin.py
genpp/ipneigh-plugin.py
genpp/iptables-plugin.py
genpp/iscsi-plugin.py
genpp/kdump-plugin.py
genpp/ldap-plugin.py
genpp/limits-plugin.py
genpp/lvm-plugin.py
genpp/main-plugin.py
genpp/mc-plugin.py
genpp/meminfo-plugin.py
genpp/misc.py
genpp/modinfo-plugin.py
genpp/modprobe-plugin.py
genpp/mount-plugin.py
genpp/mounted-plugin.py
genpp/multipath-ll-plugin.py
genpp/multipath-plugin.py
genpp/network-plugin.py
genpp/nocomment-plugin.py
genpp/nsswitch-plugin.py
genpp/ntp-plugin.py
genpp/o2cb-plugin.py
genpp/ocfs2-plugin.py
genpp/oswbb-heartbeat-plugin.py
genpp/oswtick-plugin.py
genpp/oswticker.py
genpp/oswts-plugin.py
genpp/pam-plugin.py
genpp/partitions-plugin.py
genpp/pna-plugin.py
genpp/printcap-plugin.py
genpp/printk-plugin.py
genpp/procsys-plugin.py
genpp/python.py
genpp/resolv-plugin.py
genpp/route-plugin.py
genpp/rpm-installed-plugin.py
genpp/rpm-va-plugin.py
genpp/run-me.skel
genpp/sem-plugin.py
genpp/showexport-plugin.py
genpp/slabinfo-plugin.py
genpp/smb-plugin.py
genpp/snmpd-plugin.py
genpp/ssh-plugin.py
genpp/sssd-plugin.py
genpp/superclass.py
genpp/swapon-plugin.py
genpp/sysctl-plugin.py
genpp/tcpwrapper-plugin.py
genpp/text-plugin.py
genpp/udev-plugin.py
genpp/version.py
genpp/vmcfg-plugin.py
genpp/vmstat-plugin.py
genpp/yum-plugin.py
genpp.egg-info/PKG-INFO
genpp.egg-info/SOURCES.txt
genpp.egg-info/dependency_links.txt
genpp.egg-info/entry_points.txt
genpp.egg-info/top_level.txt
samples/20-nproc.conf
samples/asmlib
samples/df
samples/dmidecode
samples/free
samples/fstab
samples/ini.conf
samples/ip-neigh
samples/limits.conf
