Metadata-Version: 1.0
Name: genpp
Version: 1.0.0
Summary: Generic Pretty Printer, using plugins
Home-page: http://www.MegaCoder.com
Author: Tommy Reynolds
Author-email: Tommy.Reynolds@MegaCoder.com
License: MIT
Platform: UNKNOWN
